.pylintrc
.stestr.conf
.zuul.yaml
AUTHORS
ChangeLog
LICENSE
README.rst
lower-constraints.txt
requirements.txt
setup.cfg
setup.py
test-requirements.txt
tox.ini
devstack/README.rst
devstack/__init__.py
devstack/functions
devstack/local_ironic.conf.sample
devstack/plugin.sh
doc/requirements.txt
doc/source/conf.py
doc/source/index.rst
doc/source/admin/index.rst
doc/source/admin/openstack-opa.rst
doc/source/admin/reference_architecture.rst
doc/source/admin/images/.gitkeep
doc/source/admin/images/ArchitectureOverview.png
doc/source/admin/images/NetworkArchitectureExample.png
doc/source/configuration/index.rst
doc/source/configuration/samples/ml2_conf.rst
doc/source/contributor/contributing.rst
doc/source/contributor/drivers_architecture.rst
doc/source/contributor/index.rst
doc/source/contributor/opa-binding.png
doc/source/contributor/quickstart.rst
doc/source/contributor/testing.rst
doc/source/contributor/usage.rst
doc/source/contributor/specs/index.rst
doc/source/install/devstack.rst
doc/source/install/index.rst
doc/source/install/installation.rst
etc/policy.json
etc/neutron/plugins/ml2/ml2_omnipath.ini
networking_omnipath.egg-info/PKG-INFO
networking_omnipath.egg-info/SOURCES.txt
networking_omnipath.egg-info/dependency_links.txt
networking_omnipath.egg-info/entry_points.txt
networking_omnipath.egg-info/not-zip-safe
networking_omnipath.egg-info/pbr.json
networking_omnipath.egg-info/requires.txt
networking_omnipath.egg-info/top_level.txt
omnipath/__init__.py
omnipath/omnipath_exceptions.py
omnipath/omnipath_thread.py
omnipath/omnipath_worker.py
omnipath/common/__init__.py
omnipath/common/constants.py
omnipath/common/omnipath_conf.py
omnipath/common/omnipath_exceptions.py
omnipath/db/__init__.py
omnipath/db/api.py
omnipath/db/models.py
omnipath/db/migration/__init__.py
omnipath/db/migration/alembic_migrations/README
omnipath/db/migration/alembic_migrations/__init__.py
omnipath/db/migration/alembic_migrations/env.py
omnipath/db/migration/alembic_migrations/script.py.mako
omnipath/db/migration/alembic_migrations/versions/CONTRACT_HEAD
omnipath/db/migration/alembic_migrations/versions/EXPAND_HEAD
omnipath/db/migration/alembic_migrations/versions/initial_branchpoint.py
omnipath/db/migration/alembic_migrations/versions/stein/expand/fe3470e95eac_add_omnipath_journal.py
omnipath/mechanism_driver/__init__.py
